{
  "packageId": "com.saeaa.store.c692ca44",
  "host": "localhost:8080",
  "name": "أسس",
  "launcherName": "أسس",
  "display": "standalone",
  "themeColor": "#6366f1",
  "navigationColor": "#6366f1",
  "backgroundColor": "#ffffff",
  "startUrl": "http://localhost:8080/",
  "iconUrl": "https://via.placeholder.com/512.png",
  "maskableIconUrl": "https://via.placeholder.com/512.png",
  "appVersion": "1.0.0",
  "appVersionCode": 1,
  "signingKey": {
    "path": "./android.keystore",
    "alias": "android"
  },
  "generatorApp": "bubblewrap-cli"
}